[
  {
    "participantNumber": "1",
    "age": "14",
    "education": "High School",
    "answers": [
      [
        "True",
        "2",
        "False",
        "3"
      ],
      [
        "True",
        "4",
        "False",
        "4"
      ],
      [
        "False",
        "4",
        "False",
        "3"
      ]
    ]
  },
  {
    "participantNumber": "1",
    "age": "4",
    "education": "High School",
    "answers": [
      [
        "True",
        4,
        "False",
        4
      ],
      [
        "True",
        4,
        "True",
        4
      ],
      [
        "Support",
        4,
        "Support",
        3
      ]
    ]
  },
  {
    "participantNumber": "1",
    "age": "1",
    "education": "no",
    "answers": [
      [
        "True",
        2,
        "True",
        3
      ],
      [
        "False",
        3,
        "False",
        3
      ],
      [
        "Against",
        3,
        "Against",
        3
      ]
    ]
  },
  {
    "participantNumber": "1",
    "age": "1",
    "education": "no",
    "answers": [
      [
        "True",
        2,
        "True",
        3
      ],
      [
        "False",
        3,
        "False",
        3
      ],
      [
        "Against",
        3,
        "Against",
        3
      ]
    ]
  },
  {
    "participantNumber": "1",
    "age": "1",
    "education": "no",
    "answers": [
      [
        "True",
        2,
        "True",
        3
      ],
      [
        "False",
        3,
        "False",
        3
      ],
      [
        "Against",
        3,
        "Against",
        4
      ]
    ]
  },
  {
    "participantNumber": "1",
    "age": "1",
    "education": "no",
    "answers": [
      [
        "True",
        2,
        "True",
        3
      ],
      [
        "False",
        3,
        "False",
        3
      ],
      [
        "Against",
        3,
        "Against",
        "4: Very certain"
      ]
    ]
  },
  {
    "participantNumber": "1",
    "age": "1",
    "education": "no",
    "answers": [
      [
        "True",
        "1: Not at all certain",
        "True",
        "1: Not at all certain"
      ],
      [
        "False",
        "1: Not at all certain",
        "True",
        "1: Not at all certain"
      ],
      [
        "Against",
        "1: Not at all certain",
        "Support",
        "1: Not at all certain"
      ]
    ]
  },
  {
    "participantNumber": "1",
    "age": "1",
    "education": "no",
    "answers": [
      [
        "True",
        "1: Not at all certain",
        "True",
        "1: Not at all certain"
      ],
      [
        "False",
        "2: Slightly certain",
        "True",
        "1: Not at all certain"
      ],
      [
        "Support",
        "1: Not at all certain",
        "Support",
        "1: Not at all certain"
      ]
    ]
  }
]